cuqipy_cil/__init__.py
cuqipy_cil/_version.py
cuqipy_cil/config.py
cuqipy_cil/model.py
cuqipy_cil/testproblem.py
cuqipy_cil-0.7.0.dist-info/licenses/LICENSE
cuqipy_cil-0.7.0.dist-info/METADATA
cuqipy_cil-0.7.0.dist-info/WHEEL
cuqipy_cil-0.7.0.dist-info/top_level.txt
cuqipy_cil-0.7.0.dist-info/RECORD
