Metadata-Version: 2.4
Name: CUQIpy-CIL
Version: 0.7.0
Summary: CUQIpy plugin for CIL
Maintainer-email: "Nicolai A. B. Riis" <nabr@dtu.dk>, "Jakob S. Jørgensen" <jakj@dtu.dk>, "Amal M. Alghamdi" <amaal@dtu.dk>, Chao Zhang <chaz@dtu.dk>
License:                                  Apache License
Project-URL: Source, https://github.com/CUQI-DTU/CUQIpy-CIL
Project-URL: Download, https://github.com/CUQI-DTU/CUQIpy-CIL/releases
Requires-Python: >=3.8
License-File: LICENSE
Requires-Dist: cuqipy
Dynamic: license-file
